seemore/__init__.py
seemore/core.py
seemore/module.py
seemore-0.1.0.dist-info/METADATA
seemore-0.1.0.dist-info/WHEEL
seemore-0.1.0.dist-info/top_level.txt
seemore-0.1.0.dist-info/RECORD
