Metadata-Version: 2.1
Name: seemore
Version: 0.1.0
Summary: A short description of your package
Author-email: Sanster <cwq1913@gmail.com>
Project-URL: Homepage, https://github.com/Sanster/seemore
Project-URL: Bug Tracker, https://github.com/Sanster/seemore/issues
Classifier: Programming Language :: Python :: 3
Classifier: License :: OSI Approved :: MIT License
Classifier: Operating System :: OS Independent
Requires-Python: >=3.7
Requires-Dist: opencv-python
Requires-Dist: torch >=1.8.0
